anyclassifier/__init__.py
anyclassifier/train_any.py
anyclassifier/annotation/__init__.py
anyclassifier/annotation/annotator.py
anyclassifier/annotation/prompt.py
anyclassifier/fasttext_wrapper/__init__.py
anyclassifier/fasttext_wrapper/config.py
anyclassifier/fasttext_wrapper/model.py
anyclassifier/fasttext_wrapper/trainer.py
anyclassifier/fasttext_wrapper/utils.py
anyclassifier/schema/__init__.py
anyclassifier/schema/schema.py
anyclassifier/synthetic_data_generation/__init__.py
anyclassifier/synthetic_data_generation/data_generator.py
anyclassifier-0.2.0.dist-info/LICENSE
anyclassifier-0.2.0.dist-info/METADATA
anyclassifier-0.2.0.dist-info/WHEEL
anyclassifier-0.2.0.dist-info/top_level.txt
anyclassifier-0.2.0.dist-info/RECORD
