Metadata-Version: 2.1
Name: anyclassifier
Version: 0.2.0
Summary: One Line To Build Any Classifier Without Data
Home-page: https://github.com/kenhktsui/anyclassifier
Download-URL: https://github.com/kenhktsui/anyclassifier/tags
Maintainer: Ken Tsui
Maintainer-email: kenhktsui@gmail.com
License: MIT
Keywords: nlp,machine learning,fewshot learning,transformers
Classifier: Intended Audience :: Developers
Classifier: Intended Audience :: Education
Classifier: Intended Audience :: Science/Research
Classifier: License :: OSI Approved :: Apache Software License
Classifier: Operating System :: OS Independent
Classifier: Programming Language :: Python :: 3
Classifier: Programming Language :: Python :: 3.8
Classifier: Programming Language :: Python :: 3.9
Classifier: Topic :: Scientific/Engineering :: Artificial Intelligence
License-File: LICENSE
Requires-Dist: datasets >=2.20.0
Requires-Dist: setfit >=1.0.3
Requires-Dist: huggingface-hub ==0.23.5
Requires-Dist: llama-cpp-python ==0.2.88
Requires-Dist: fasttext ==0.9.3
Requires-Dist: transformers ==4.39.0
